SharedTableBroker/SharedTableBroker.py
SharedTableBroker/__init__.py
SharedTableBroker-0.1.3.dist-info/LICENSE
SharedTableBroker-0.1.3.dist-info/METADATA
SharedTableBroker-0.1.3.dist-info/WHEEL
SharedTableBroker-0.1.3.dist-info/top_level.txt
SharedTableBroker-0.1.3.dist-info/RECORD
